<?xml version="1.0" encoding="UTF-8"?>
<beans xmlns="http://www.springframework.org/schema/beans"
	xmlns:xsi="http://www.w3.org/2001/XMLSchema-instance" xmlns:context="http://www.springframework.org/schema/context"
	xsi:schemaLocation="http://www.springframework.org/schema/beans http://www.springframework.org/schema/beans/spring-beans-3.2.xsd
        http://www.springframework.org/schema/context http://www.springframework.org/schema/context/spring-context-3.2.xsd
        http://www.springframework.org/schema/tx http://www.springframework.org/schema/tx/spring-tx.xsd"
	default-autowire="byName">

	<!-- Abstract bean, where all common fields are stored -->
	<bean id="defaultFacade" abstract="true">
		<property name="pagedRequestConverter" ref="pagedRequestConverter" />
		<property name="pagedResultConverter" ref="pagedSearchConverter" />
		<property name="updateConverter" ref="updateConverter" />
		<property name="insertConverter" ref="insertConverter" />
		<property name="entityDetailsConverter" ref="entityDetailsConverter"/>
	</bean>

	<bean id="broadcastingFacade" class="org.lnu.is.facade.facade.broadcasting.BroadcastingFacade" parent="defaultFacade">
		<property name="resourceConverter" ref="broadcastingResourceConverter" />
		<property name="entityConverter" ref="broadcastingConverter" />
		<property name="service" ref="broadcastingService" />
		<property name="broadcastResourceEmailConverter" ref="broadcastingEmailConverter"/>
		<property name="emailBroadcastingConverter" ref="emailBroadcastingConverter"/>
		<property name="broadcastinConverter" ref="broadcastingBroadcastingConverter"/>
		<property name="mailService" ref="defaultMailService"/>
	</bean>
	
	<bean id="operationTypeFacade" class="org.lnu.is.facade.facade.DefaultFacade" parent="defaultFacade">
		<property name="resourceConverter" ref="operationTypeResourceConverter" />
		<property name="entityConverter" ref="operationTypeConverter" />
		<property name="service" ref="operationTypeService" />
	</bean>
	
	<bean id="adminUnitFacade" class="org.lnu.is.facade.facade.DefaultFacade" parent="defaultFacade">
		<property name="resourceConverter" ref="adminUnitResourceConverter" />
		<property name="entityConverter" ref="adminUnitConverter" />
		<property name="service" ref="adminUnitService" />
	</bean>

	<bean id="adminUnitTypeFacade" class="org.lnu.is.facade.facade.DefaultFacade" parent="defaultFacade">
		<property name="resourceConverter" ref="adminUnitTypeResourceConverter" />
		<property name="entityConverter" ref="adminUnitTypeConverter" />
		<property name="service" ref="adminUnitTypeService" />
	</bean>

	<bean id="assetFacade" class="org.lnu.is.facade.facade.DefaultFacade" parent="defaultFacade">
		<property name="resourceConverter" ref="assetResourceConverter" />
		<property name="entityConverter" ref="assetConverter" />
		<property name="service" ref="assetService" />
	</bean>

	<bean id="assetAddressFacade" class="org.lnu.is.facade.facade.DefaultFacade" parent="defaultFacade">
		<property name="resourceConverter" ref="assetAddressResourceConverter" />
		<property name="entityConverter" ref="assetAddressConverter" />
		<property name="service" ref="assetAddressService" />
	</bean>

	<bean id="assetStateFacade" class="org.lnu.is.facade.facade.DefaultFacade" parent="defaultFacade">
		<property name="resourceConverter" ref="assetStateResourceConverter" />
		<property name="entityConverter" ref="assetStateConverter" />
		<property name="service" ref="assetStateService" />
	</bean>

	<bean id="assetStatusFacade" class="org.lnu.is.facade.facade.DefaultFacade" parent="defaultFacade">
		<property name="resourceConverter" ref="assetStatusResourceConverter" />
		<property name="entityConverter" ref="assetStatusConverter" />
		<property name="service" ref="assetStatusService" />
	</bean>

	<bean id="assetTypeFacade" class="org.lnu.is.facade.facade.DefaultFacade" parent="defaultFacade">
		<property name="resourceConverter" ref="assetTypeResourceConverter" />
		<property name="entityConverter" ref="assetTypeConverter" />
		<property name="service" ref="assetTypeService" />
	</bean>

	<bean id="benefitFacade" class="org.lnu.is.facade.facade.DefaultFacade" parent="defaultFacade">
		<property name="resourceConverter" ref="benefitResourceConverter" />
		<property name="entityConverter" ref="benefitConverter" />
		<property name="service" ref="benefitService" />
	</bean>

	<bean id="benefitTypeFacade" class="org.lnu.is.facade.facade.DefaultFacade" parent="defaultFacade">
		<property name="resourceConverter" ref="benefitTypeResourceConverter" />
		<property name="entityConverter" ref="benefitTypeConverter" />
		<property name="service" ref="benefitTypeService" />
	</bean>

	<bean id="contactTypeFacade" class="org.lnu.is.facade.facade.DefaultFacade" parent="defaultFacade">
		<property name="resourceConverter" ref="contactTypeResourceConverter" />
		<property name="entityConverter" ref="contactTypeConverter" />
		<property name="service" ref="contactTypeService" />
	</bean>

	<bean id="courseTypeFacade" class="org.lnu.is.facade.facade.DefaultFacade" parent="defaultFacade">
		<property name="resourceConverter" ref="courseTypeResourceConverter" />
		<property name="entityConverter" ref="courseTypeConverter" />
		<property name="service" ref="courseTypeService" />
	</bean>

	<bean id="employeeFacade" class="org.lnu.is.facade.facade.DefaultFacade" parent="defaultFacade">
		<property name="resourceConverter" ref="employeeResourceConverter" />
		<property name="entityConverter" ref="employeeConverter" />
		<property name="service" ref="employeeService" />
	</bean>

	<bean id="employeeTypeFacade" class="org.lnu.is.facade.facade.DefaultFacade" parent="defaultFacade">
		<property name="resourceConverter" ref="employeeTypeResourceConverter" />
		<property name="entityConverter" ref="employeeTypeConverter" />
		<property name="service" ref="employeeTypeService" />
	</bean>

	<bean id="employeeStatusFacade" class="org.lnu.is.facade.facade.DefaultFacade" parent="defaultFacade">
		<property name="resourceConverter" ref="employeeStatusResourceConverter" />
		<property name="entityConverter" ref="employeeStatusConverter" />
		<property name="service" ref="employeeStatusService" />
	</bean>

	<bean id="enrolmentTypeFacade" class="org.lnu.is.facade.facade.DefaultFacade" parent="defaultFacade">
		<property name="resourceConverter" ref="enrolmentTypeResourceConverter" />
		<property name="entityConverter" ref="enrolmentTypeConverter" />
		<property name="service" ref="enrolmentTypeService" />
	</bean>

	<bean id="enrolmentFacade" class="org.lnu.is.facade.facade.DefaultFacade" parent="defaultFacade">
		<property name="resourceConverter" ref="enrolmentResourceConverter" />
		<property name="entityConverter" ref="enrolmentConverter" />
		<property name="service" ref="enrolmentService" />
	</bean>

	<bean id="enrolmentBenefitFacade" class="org.lnu.is.facade.facade.DefaultFacade" parent="defaultFacade">
		<property name="resourceConverter" ref="enrolmentBenefitResourceConverter" />
		<property name="entityConverter" ref="enrolmentBenefitConverter" />
		<property name="service" ref="enrolmentBenefitService" />
	</bean>

	<bean id="enrolmentStatusFacade" class="org.lnu.is.facade.facade.DefaultFacade" parent="defaultFacade">
		<property name="resourceConverter" ref="enrolmentStatusResourceConverter" />
		<property name="entityConverter" ref="enrolmentStatusConverter" />
		<property name="service" ref="enrolmentStatusService" />
	</bean>

	<bean id="honorTypeFacade" class="org.lnu.is.facade.facade.DefaultFacade" parent="defaultFacade">
		<property name="resourceConverter" ref="honorTypeResourceConverter" />
		<property name="entityConverter" ref="honorTypeConverter" />
		<property name="service" ref="honorTypeService" />
	</bean>

	<bean id="addressTypeFacade" class="org.lnu.is.facade.facade.DefaultFacade" parent="defaultFacade">
		<property name="resourceConverter" ref="addressTypeResourceConverter" />
		<property name="entityConverter" ref="addressTypeConverter" />
		<property name="service" ref="addressTypeService" />
	</bean>

	<bean id="departmentFacade" class="org.lnu.is.facade.facade.DefaultFacade" parent="defaultFacade">
		<property name="resourceConverter" ref="departmentResourceConverter" />
		<property name="entityConverter" ref="departmentConverter" />
		<property name="service" ref="departmentService" />
	</bean>

	<bean id="departmentAddressFacade" class="org.lnu.is.facade.facade.DefaultFacade" parent="defaultFacade">
		<property name="resourceConverter" ref="departmentAddressResourceConverter" />
		<property name="entityConverter" ref="departmentAddressConverter" />
		<property name="service" ref="departmentAddressService" />
	</bean>

	<bean id="departmentContactFacade" class="org.lnu.is.facade.facade.DefaultFacade" parent="defaultFacade">
		<property name="resourceConverter" ref="departmentContactResourceConverter" />
		<property name="entityConverter" ref="departmentContactConverter" />
		<property name="service" ref="departmentContactService" />
	</bean>

	<bean id="departmentNameFacade" class="org.lnu.is.facade.facade.DefaultFacade" parent="defaultFacade">
		<property name="resourceConverter" ref="departmentNameResourceConverter" />
		<property name="entityConverter" ref="departmentNameConverter" />
		<property name="service" ref="departmentNameService" />
	</bean>

	<bean id="departmentSpecialtyFacade" class="org.lnu.is.facade.facade.DefaultFacade" parent="defaultFacade">
		<property name="resourceConverter" ref="departmentSpecialtyResourceConverter" />
		<property name="entityConverter" ref="departmentSpecialtyConverter" />
		<property name="service" ref="departmentSpecialtyService" />
	</bean>

	<bean id="departmentTypeFacade" class="org.lnu.is.facade.facade.DefaultFacade" parent="defaultFacade">
		<property name="resourceConverter" ref="departmentTypeResourceConverter" />
		<property name="entityConverter" ref="departmentTypeConverter" />
		<property name="service" ref="departmentTypeService" />
	</bean>

	<bean id="degreeFacade" class="org.lnu.is.facade.facade.DefaultFacade" parent="defaultFacade">
		<property name="resourceConverter" ref="degreeResourceConverter" />
		<property name="entityConverter" ref="degreeConverter" />
		<property name="service" ref="degreeService" />
	</bean>

	<bean id="degreeTypeFacade" class="org.lnu.is.facade.facade.DefaultFacade" parent="defaultFacade">
		<property name="resourceConverter" ref="degreeTypeResourceConverter" />
		<property name="entityConverter" ref="degreeTypeConverter" />
		<property name="service" ref="degreeTypeService" />
	</bean>

	<bean id="dutyTypeFacade" class="org.lnu.is.facade.facade.DefaultFacade" parent="defaultFacade">
		<property name="resourceConverter" ref="dutyTypeResourceConverter" />
		<property name="entityConverter" ref="dutyTypeConverter" />
		<property name="service" ref="dutyTypeService" />
	</bean>

	<bean id="educationTypeFacade" class="org.lnu.is.facade.facade.DefaultFacade" parent="defaultFacade">
		<property name="resourceConverter" ref="educationTypeResourceConverter" />
		<property name="entityConverter" ref="educationTypeConverter" />
		<property name="service" ref="educationTypeService" />
	</bean>

	<bean id="eduFormTypeFacade" class="org.lnu.is.facade.facade.DefaultFacade" parent="defaultFacade">
		<property name="resourceConverter" ref="eduFormTypeResourceConverter" />
		<property name="entityConverter" ref="eduFormTypeConverter" />
		<property name="service" ref="eduFormTypeService" />
	</bean>

	<bean id="enrolmentStatusTypeFacade" class="org.lnu.is.facade.facade.DefaultFacade" parent="defaultFacade">
		<property name="resourceConverter" ref="enrolmentStatusTypeResourceConverter" />
		<property name="entityConverter" ref="enrolmentStatusTypeConverter" />
		<property name="service" ref="enrolmentStatusTypeService" />
	</bean>

	<bean id="enrolmentSubjectFacade" class="org.lnu.is.facade.facade.DefaultFacade" parent="defaultFacade">
		<property name="resourceConverter" ref="enrolmentSubjectResourceConverter" />
		<property name="entityConverter" ref="enrolmentSubjectConverter" />
		<property name="service" ref="enrolmentSubjectService" />
	</bean>

	<bean id="genderTypeFacade" class="org.lnu.is.facade.facade.DefaultFacade" parent="defaultFacade">
		<property name="resourceConverter" ref="genderTypeResourceConverter" />
		<property name="entityConverter" ref="genderTypeConverter" />
		<property name="service" ref="genderTypeService" />
	</bean>

	<bean id="jobTypeFacade" class="org.lnu.is.facade.facade.DefaultFacade" parent="defaultFacade">
		<property name="resourceConverter" ref="jobTypeResourceConverter" />
		<property name="entityConverter" ref="jobTypeConverter" />
		<property name="service" ref="jobTypeService" />
	</bean>

	<bean id="languageFacade" class="org.lnu.is.facade.facade.DefaultFacade" parent="defaultFacade">
		<property name="resourceConverter" ref="languageResourceConverter" />
		<property name="entityConverter" ref="languageConverter" />
		<property name="service" ref="languageService" />
	</bean>

	<bean id="marriedTypeFacade" class="org.lnu.is.facade.facade.DefaultFacade" parent="defaultFacade">
		<property name="resourceConverter" ref="marriedTypeResourceConverter" />
		<property name="entityConverter" ref="marriedTypeConverter" />
		<property name="service" ref="marriedTypeService" />
	</bean>

	<bean id="paperTypeFacade" class="org.lnu.is.facade.facade.DefaultFacade" parent="defaultFacade">
		<property name="resourceConverter" ref="paperTypeResourceConverter" />
		<property name="entityConverter" ref="paperTypeConverter" />
		<property name="service" ref="paperTypeService" />
	</bean>
	
	<bean id="paperUsageFacade" class="org.lnu.is.facade.facade.DefaultFacade" parent="defaultFacade">
		<property name="resourceConverter" ref="paperUsageResourceConverter" />
		<property name="entityConverter" ref="paperUsageConverter" />
		<property name="service" ref="paperUsageService" />
	</bean>

	<bean id="partnerFacade" class="org.lnu.is.facade.facade.DefaultFacade" parent="defaultFacade">
		<property name="resourceConverter" ref="partnerResourceConverter" />
		<property name="entityConverter" ref="partnerConverter" />
		<property name="service" ref="partnerService" />
	</bean>

	<bean id="personFacade" class="org.lnu.is.facade.facade.DefaultFacade" parent="defaultFacade">
		<property name="resourceConverter" ref="personResourceConverter" />
		<property name="entityConverter" ref="personConverter" />
		<property name="service" ref="personService" />
	</bean>

	<bean id="personFamilyFacade" class="org.lnu.is.facade.facade.DefaultFacade" parent="defaultFacade">
		<property name="resourceConverter" ref="personFamilyResourceConverter" />
		<property name="entityConverter" ref="personFamilyConverter" />
		<property name="service" ref="personFamilyService" />
	</bean>

	<bean id="personAddressFacade" class="org.lnu.is.facade.facade.DefaultFacade" parent="defaultFacade">
		<property name="resourceConverter" ref="personAddressResourceConverter" />
		<property name="entityConverter" ref="personAddressConverter" />
		<property name="service" ref="personAddressService" />
	</bean>

	<bean id="personAwardFacade" class="org.lnu.is.facade.facade.DefaultFacade" parent="defaultFacade">
		<property name="resourceConverter" ref="personAwardResourceConverter" />
		<property name="entityConverter" ref="personAwardConverter" />
		<property name="service" ref="personAwardService" />
	</bean>

	<bean id="personEducationFacade" class="org.lnu.is.facade.facade.DefaultFacade" parent="defaultFacade">
		<property name="resourceConverter" ref="personEducationResourceConverter" />
		<property name="entityConverter" ref="personEducationConverter" />
		<property name="service" ref="personEducationService" />
	</bean>

	<bean id="personEnrolmentSubjectFacade" class="org.lnu.is.facade.facade.DefaultFacade" parent="defaultFacade">
		<property name="resourceConverter" ref="personEnrolmentSubjectResourceConverter" />
		<property name="entityConverter" ref="personEnrolmentSubjectConverter" />
		<property name="service" ref="personEnrolmentSubjectService" />
	</bean>

	<bean id="personContactFacade" class="org.lnu.is.facade.facade.DefaultFacade" parent="defaultFacade">
		<property name="resourceConverter" ref="personContactResourceConverter" />
		<property name="entityConverter" ref="personContactConverter" />
		<property name="service" ref="personContactService" />
	</bean>
	
	<bean id="personPaperFacade" class="org.lnu.is.facade.facade.DefaultFacade" parent="defaultFacade">
		<property name="resourceConverter" ref="personPaperResourceConverter" />
		<property name="entityConverter" ref="personPaperConverter" />
		<property name="service" ref="personPaperService" />
	</bean>
	
	<bean id="personPensionFacade" class="org.lnu.is.facade.facade.DefaultFacade" parent="defaultFacade">
		<property name="resourceConverter" ref="personPensionResourceConverter" />
		<property name="entityConverter" ref="personPensionConverter" />
		<property name="service" ref="personPensionService" />
	</bean>

	<bean id="personNameFacade" class="org.lnu.is.facade.facade.DefaultFacade" parent="defaultFacade">
		<property name="resourceConverter" ref="personNameResourceConverter" />
		<property name="entityConverter" ref="personNameConverter" />
		<property name="service" ref="personNameService" />
	</bean>

	<bean id="personTypeFacade" class="org.lnu.is.facade.facade.DefaultFacade" parent="defaultFacade">
		<property name="resourceConverter" ref="personTypeResourceConverter" />
		<property name="entityConverter" ref="personTypeConverter" />
		<property name="service" ref="personTypeService" />
	</bean>

	<bean id="personLanguageFacade" class="org.lnu.is.facade.facade.DefaultFacade" parent="defaultFacade">
		<property name="resourceConverter" ref="personLanguageResourceConverter" />
		<property name="entityConverter" ref="personLanguageConverter" />
		<property name="service" ref="personLanguageService" />
	</bean>

	<bean id="personWorkFacade" class="org.lnu.is.facade.facade.DefaultFacade" parent="defaultFacade">
		<property name="resourceConverter" ref="personWorkResourceConverter" />
		<property name="entityConverter" ref="personWorkConverter" />
		<property name="service" ref="personWorkService" />
	</bean>

	<bean id="publicActivityFacade" class="org.lnu.is.facade.facade.DefaultFacade" parent="defaultFacade">
		<property name="resourceConverter" ref="publicActivityResourceConverter" />
		<property name="entityConverter" ref="publicActivityConverter" />
		<property name="service" ref="publicActivityService" />
	</bean>

	<bean id="publicActivityAwardFacade" class="org.lnu.is.facade.facade.DefaultFacade" parent="defaultFacade">
		<property name="resourceConverter" ref="publicActivityAwardResourceConverter" />
		<property name="entityConverter" ref="publicActivityAwardConverter" />
		<property name="service" ref="publicActivityAwardService" />
	</bean>

	<bean id="publicActivityTypeFacade" class="org.lnu.is.facade.facade.DefaultFacade" parent="defaultFacade">
		<property name="resourceConverter" ref="publicActivityTypeResourceConverter" />
		<property name="entityConverter" ref="publicActivityTypeConverter" />
		<property name="service" ref="publicActivityTypeService" />
	</bean>

	<bean id="reasonFacade" class="org.lnu.is.facade.facade.DefaultFacade" parent="defaultFacade">
		<property name="resourceConverter" ref="reasonResourceConverter" />
		<property name="entityConverter" ref="reasonConverter" />
		<property name="service" ref="reasonService" />
	</bean>

	<bean id="sallaryTypeFacade" class="org.lnu.is.facade.facade.DefaultFacade" parent="defaultFacade">
		<property name="resourceConverter" ref="sallaryTypeResourceConverter" />
		<property name="entityConverter" ref="sallaryTypeConverter" />
		<property name="service" ref="sallaryTypeService" />
	</bean>

	<bean id="streetTypeFacade" class="org.lnu.is.facade.facade.DefaultFacade" parent="defaultFacade">
		<property name="resourceConverter" ref="streetTypeResourceConverter" />
		<property name="entityConverter" ref="streetTypeConverter" />
		<property name="service" ref="streetTypeService" />
	</bean>

	<bean id="specialtyFacade" class="org.lnu.is.facade.facade.DefaultFacade" parent="defaultFacade">
		<property name="resourceConverter" ref="specialtyResourceConverter" />
		<property name="entityConverter" ref="specialtyConverter" />
		<property name="service" ref="specialtyService" />
	</bean>

	<bean id="specialtyTypeFacade" class="org.lnu.is.facade.facade.DefaultFacade" parent="defaultFacade">
		<property name="resourceConverter" ref="specialtyTypeResourceConverter" />
		<property name="entityConverter" ref="specialtyTypeConverter" />
		<property name="service" ref="specialtyTypeService" />
	</bean>

	<bean id="specOfferFacade" class="org.lnu.is.facade.facade.DefaultFacade" parent="defaultFacade">
		<property name="resourceConverter" ref="specOfferResourceConverter" />
		<property name="entityConverter" ref="specOfferConverter" />
		<property name="service" ref="specOfferService" />
	</bean>

	<bean id="specOfferSubjectFacade" class="org.lnu.is.facade.facade.DefaultFacade" parent="defaultFacade">
		<property name="resourceConverter" ref="specOfferSubjectResourceConverter" />
		<property name="entityConverter" ref="specOfferSubjectConverter" />
		<property name="service" ref="specOfferSubjectService" />
	</bean>

	<bean id="specOfferTypeFacade" class="org.lnu.is.facade.facade.DefaultFacade" parent="defaultFacade">
		<property name="resourceConverter" ref="specOfferTypeResourceConverter" />
		<property name="entityConverter" ref="specOfferTypeConverter" />
		<property name="service" ref="specOfferTypeService" />
	</bean>

	<bean id="specOfferWaveFacade" class="org.lnu.is.facade.facade.DefaultFacade" parent="defaultFacade">
		<property name="resourceConverter" ref="specOfferWaveResourceConverter" />
		<property name="entityConverter" ref="specOfferWaveConverter" />
		<property name="service" ref="specOfferWaveService" />
	</bean>

	<bean id="subjectFacade" class="org.lnu.is.facade.facade.DefaultFacade" parent="defaultFacade">
		<property name="resourceConverter" ref="subjectResourceConverter" />
		<property name="entityConverter" ref="subjectConverter" />
		<property name="service" ref="subjectService" />
	</bean>

	<bean id="subjectTypeFacade" class="org.lnu.is.facade.facade.DefaultFacade" parent="defaultFacade">
		<property name="resourceConverter" ref="subjectTypeResourceConverter" />
		<property name="entityConverter" ref="subjectTypeConverter" />
		<property name="service" ref="subjectTypeService" />
	</bean>
	
	<bean id="orderFacade" class="org.lnu.is.facade.facade.DefaultFacade" parent="defaultFacade">
		<property name="resourceConverter" ref="orderResourceConverter" />
		<property name="entityConverter" ref="orderConverter" />
		<property name="service" ref="orderService" />
	</bean>

	<bean id="orderTypeFacade" class="org.lnu.is.facade.facade.DefaultFacade" parent="defaultFacade">
		<property name="resourceConverter" ref="orderTypeResourceConverter" />
		<property name="entityConverter" ref="orderTypeConverter" />
		<property name="service" ref="orderTypeService" />
	</bean>

	<bean id="familyTypeFacade" class="org.lnu.is.facade.facade.DefaultFacade" parent="defaultFacade">
		<property name="resourceConverter" ref="familyTypeResourceConverter" />
		<property name="entityConverter" ref="familyTypeConverter" />
		<property name="service" ref="familyTypeService" />
	</bean>

	<bean id="timePeriodFacade" class="org.lnu.is.facade.facade.DefaultFacade" parent="defaultFacade">
		<property name="resourceConverter" ref="timePeriodResourceConverter" />
		<property name="entityConverter" ref="timePeriodConverter" />
		<property name="service" ref="timePeriodService" />
	</bean>

	<bean id="timePeriodTypeFacade" class="org.lnu.is.facade.facade.DefaultFacade" parent="defaultFacade">
		<property name="resourceConverter" ref="timePeriodTypeResourceConverter" />
		<property name="entityConverter" ref="timePeriodTypeConverter" />
		<property name="service" ref="timePeriodTypeService" />
	</bean>
	
	<bean id="timeSheetTypeFacade" class="org.lnu.is.facade.facade.DefaultFacade" parent="defaultFacade">
		<property name="resourceConverter" ref="timeSheetTypeResourceConverter" />
		<property name="entityConverter" ref="timeSheetTypeConverter" />
		<property name="service" ref="timeSheetTypeService" />
	</bean>

	<bean id="specOfferBenefitFacade" class="org.lnu.is.facade.facade.DefaultFacade" parent="defaultFacade">
		<property name="resourceConverter" ref="specOfferBenefitResourceConverter" />
		<property name="entityConverter" ref="specOfferBenefitConverter" />
		<property name="service" ref="specOfferBenefitService" />
	</bean>
	
	<bean id="waveTypeFacade" class="org.lnu.is.facade.facade.DefaultFacade" parent="defaultFacade">
		<property name="resourceConverter" ref="waveTypeResourceConverter" />
		<property name="entityConverter" ref="waveTypeConverter" />
		<property name="service" ref="waveTypeService" />
	</bean>
	
</beans>
